choosegpu/__init__.py
choosegpu-0.0.1.dist-info/LICENSE
choosegpu-0.0.1.dist-info/METADATA
choosegpu-0.0.1.dist-info/WHEEL
choosegpu-0.0.1.dist-info/top_level.txt
choosegpu-0.0.1.dist-info/RECORD
